latitude_sdk/__init__.py
latitude_sdk/py.typed
latitude_sdk/client/__init__.py
latitude_sdk/client/client.py
latitude_sdk/client/payloads.py
latitude_sdk/client/router.py
latitude_sdk/env/__init__.py
latitude_sdk/env/env.py
latitude_sdk/sdk/__init__.py
latitude_sdk/sdk/errors.py
latitude_sdk/sdk/evaluations.py
latitude_sdk/sdk/latitude.py
latitude_sdk/sdk/logs.py
latitude_sdk/sdk/projects.py
latitude_sdk/sdk/prompts.py
latitude_sdk/sdk/runs.py
latitude_sdk/sdk/stream.py
latitude_sdk/sdk/types.py
latitude_sdk/sdk/versions.py
latitude_sdk/util/__init__.py
latitude_sdk/util/utils.py
latitude_sdk/version/__init__.py
latitude_sdk/version/version.py
latitude_sdk-5.4.0.dist-info/METADATA
latitude_sdk-5.4.0.dist-info/WHEEL
latitude_sdk-5.4.0.dist-info/licenses/LICENSE.md
latitude_sdk-5.4.0.dist-info/RECORD
