Metadata-Version: 2.4
Name: latitude-sdk
Version: 5.4.0
Summary: Latitude SDK for Python
Project-URL: repository, https://github.com/latitude-dev/latitude-llm/tree/main/packages/sdks/python
Project-URL: homepage, https://github.com/latitude-dev/latitude-llm/tree/main/packages/sdks/python#readme
Project-URL: documentation, https://github.com/latitude-dev/latitude-llm/tree/main/packages/sdks/python#readme
Author-email: Latitude Data SL <hello@latitude.so>
Maintainer-email: Latitude Data SL <hello@latitude.so>
License-Expression: MIT
License-File: LICENSE.md
Requires-Python: <3.14,>=3.9
Requires-Dist: httpx-sse>=0.4.1
Requires-Dist: httpx>=0.28.1
Requires-Dist: promptl-ai>=1.2.0
Requires-Dist: pydantic>=2.11.9
Requires-Dist: typing-extensions>=4.15.0
